django_umsebenzi-1.4.0.dist-info/licenses/LICENSE
umsebenzi/__init__.py
umsebenzi/admin.py
umsebenzi/apps.py
umsebenzi/enums.py
umsebenzi/exceptions.py
umsebenzi/filters.py
umsebenzi/forms.py
umsebenzi/latest.py
umsebenzi/models.py
umsebenzi/serializers.py
umsebenzi/urls.py
umsebenzi/views.py
umsebenzi/migrations/0001_initial.py
umsebenzi/migrations/0002_task_issue_task_parent.py
umsebenzi/migrations/0003_alter_task_due_date_alter_task_parent.py
umsebenzi/migrations/__init__.py
django_umsebenzi-1.4.0.dist-info/METADATA
django_umsebenzi-1.4.0.dist-info/WHEEL
django_umsebenzi-1.4.0.dist-info/top_level.txt
django_umsebenzi-1.4.0.dist-info/RECORD
