Metadata-Version: 2.4
Name: django-umsebenzi
Version: 1.4.0
Summary: 'A set of django rest apis to manage your personal projects and tasks'
Home-page: https://github.com/StandaloneDynamics/django-umsebenzi
Author: Menzi Mthembu
License: GPL v3.0
Classifier: Environment :: Web Environment
Classifier: Framework :: Django
Classifier: Framework :: Django :: 4.2
Classifier: Intended Audience :: Developers
Classifier: License :: OSI Approved :: GNU General Public License v3 (GPLv3)
Classifier: Operating System :: OS Independent
Classifier: Programming Language :: Python
Classifier: Programming Language :: Python :: 3
Classifier: Programming Language :: Python :: 3 :: Only
Classifier: Programming Language :: Python :: 3.9
Classifier: Programming Language :: Python :: 3.10
Classifier: Programming Language :: Python :: 3.11
Classifier: Topic :: Internet :: WWW/HTTP
Classifier: Topic :: Internet :: WWW/HTTP :: Dynamic Content
Requires-Python: >=3.9
License-File: LICENSE
Requires-Dist: django~=4.2
Requires-Dist: djangorestframework~=3.14
Requires-Dist: django_enumfield~=3.1
Requires-Dist: django-filter~=23.5
Requires-Dist: drf-spectacular~=0.28.0
Dynamic: license-file
